comfy_commander/__init__.py
comfy_commander/core.py
comfy_commander-0.1.2.dist-info/METADATA
comfy_commander-0.1.2.dist-info/WHEEL
comfy_commander-0.1.2.dist-info/top_level.txt
comfy_commander-0.1.2.dist-info/RECORD
