Metadata-Version: 2.4
Name: comfy-commander
Version: 0.1.2
Summary: A package for programmatically running ComfyUI workloads either locally or remotely
Home-page: https://github.com/nathanhalko/comfy-commander
Author: Nathan Halko
Author-email: Nathan Halko <nathan@halko.us>
License: MIT
Project-URL: Homepage, https://github.com/halkony/comfy-commander
Project-URL: Repository, https://github.com/halkony/comfy-commander
Project-URL: Issues, https://github.com/halkony/comfy-commander/issues
Keywords: comfyui,workflow,automation,ai,image-generation
Classifier: Development Status :: 3 - Alpha
Classifier: Intended Audience :: Developers
Classifier: License :: OSI Approved :: MIT License
Classifier: Programming Language :: Python :: 3
Classifier: Programming Language :: Python :: 3.8
Classifier: Programming Language :: Python :: 3.9
Classifier: Programming Language :: Python :: 3.10
Classifier: Programming Language :: Python :: 3.11
Classifier: Programming Language :: Python :: 3.12
Classifier: Topic :: Software Development :: Libraries :: Python Modules
Classifier: Topic :: Scientific/Engineering :: Artificial Intelligence
Requires-Python: >=3.8
Requires-Dist: requests>=2.32.0
Requires-Dist: pillow>=11.0.0
Requires-Dist: attrs>=25.0.0
Dynamic: author
Dynamic: home-page
Dynamic: requires-python
